quri_parts/algo/NOTICE
quri_parts/algo/__init__.py
quri_parts/algo/ansatz/__init__.py
quri_parts/algo/ansatz/hardware_efficient.py
quri_parts/algo/ansatz/symmetry_preserving.py
quri_parts/algo/ansatz/two_local.py
quri_parts/algo/mitigation/__init__.py
quri_parts/algo/mitigation/cdr/__init__.py
quri_parts/algo/mitigation/cdr/cdr.py
quri_parts/algo/mitigation/post_selection/__init__.py
quri_parts/algo/mitigation/post_selection/post_selection.py
quri_parts/algo/mitigation/readout_mitigation/__init__.py
quri_parts/algo/mitigation/readout_mitigation/readout_mitigation.py
quri_parts/algo/mitigation/zne/__init__.py
quri_parts/algo/mitigation/zne/zne.py
quri_parts/algo/optimizer/__init__.py
quri_parts/algo/optimizer/adam.py
quri_parts/algo/optimizer/interface.py
quri_parts/algo/optimizer/lbfgs.py
quri_parts/algo/optimizer/nft.py
quri_parts/algo/optimizer/spsa.py
quri_parts/algo/optimizer/tolerance.py
quri_parts/algo/py.typed
quri_parts/algo/utils/__init__.py
quri_parts/algo/utils/fitting.py
quri_parts_algo-17.0.0.dist-info/LICENSE
quri_parts_algo-17.0.0.dist-info/METADATA
quri_parts_algo-17.0.0.dist-info/WHEEL
quri_parts_algo-17.0.0.dist-info/RECORD
